defergo/__init__.py
defergo-0.0.5.dist-info/METADATA
defergo-0.0.5.dist-info/WHEEL
defergo-0.0.5.dist-info/top_level.txt
defergo-0.0.5.dist-info/RECORD
